{
  "entries": [
    {
      "id": "https-www-slobodnaevropa-org-a-33783162-html",
      "title": "Šta se zna o optužbama za 'prinudni rad' zbog kojih Ziđin ne može da izvozi bakar iz Srbije u SAD?",
      "url": "https://www.slobodnaevropa.org/a/33783162.html",
      "date": "2026-06-17",
      "datetime": "2026-06-17T17:10:06+00:00",
      "time": "17:10",
      "source": "RSE Balkan",
      "category": "Плате и зараде",
      "summary": "",
      "breaking": true,
      "alert": true,
      "priority": 184
    },
    {
      "id": "a-benda-hitno-se-oglasili-iz-grupe-i-otkazali-nastup-vcbemln",
      "title": "POZLILO VLADI IZ MAGLA BENDA Hitno se oglasili iz grupe i otkazali nastup: \"Žao nam je, odluka nije bila laka\"",
      "url": "https://www.blic.rs/zabava/pozlilo-vladi-iz-magla-benda-hitno-se-oglasili-iz-grupe-i-otkazali-nastup/vcbemln",
      "date": "2026-06-19",
      "datetime": "2026-06-19T20:04:43+00:00",
      "time": "20:04",
      "source": "Blic",
      "category": "Радничка права",
      "summary": "",
      "breaking": true,
      "alert": false,
      "priority": 100
    },
    {
      "id": "trajne-atmosfere-nekaznjivosti-institucije-hitno-da-reaguju-",
      "title": "NUNS i ANEM: Pretnje Veranu Matiću i N1 su  posledica dugotrajne atmosfere nekažnjivosti, institucije hitno da reaguju",
      "url": "https://nova.rs/vesti/drustvo/nuns-i-anem-pretnje-veranu-maticu-i-n1-su-posledica-dugotrajne-atmosfere-nekaznjivosti-institucije-hitno-da-reaguju/",
      "date": "2026-06-19",
      "datetime": "2026-06-19T18:42:01+00:00",
      "time": "18:42",
      "source": "Nova",
      "category": "Извршења",
      "summary": "",
      "breaking": true,
      "alert": false,
      "priority": 100
    },
    {
      "id": "trajne-atmosfere-nekaznjivosti-institucije-hitno-da-reaguju-",
      "title": "NUNS i ANEM: Nove brutalne pretnje Veranu Matiću i TV N1 posledica dugotrajne atmosfere nekažnjivosti – institucije hitno da reaguju",
      "url": "https://n1info.rs/vesti/nuns-i-anem-nove-brutalne-pretnje-veranu-maticu-i-tv-n1-posledica-dugotrajne-atmosfere-nekaznjivosti-institucije-hitno-da-reaguju/",
      "date": "2026-06-19",
      "datetime": "2026-06-19T17:57:14+00:00",
      "time": "17:57",
      "source": "N1",
      "category": "Извршења",
      "summary": "",
      "breaking": true,
      "alert": false,
      "priority": 100
    },
    {
      "id": "ar-uhapsen-u-los-andjelesu-preti-mu-11-godina-robije-tjpdqff",
      "title": "UHAPŠEN POZNATI KOMIČAR  Preti mu 11 godina robije: Kolege ga optuživale za krađu viceva",
      "url": "https://www.blic.rs/kultura/poznati-komicar-uhapsen-u-los-andjelesu-preti-mu-11-godina-robije/tjpdqff",
      "date": "2026-06-19",
      "datetime": "2026-06-19T17:00:00+00:00",
      "time": "17:00",
      "source": "Blic",
      "category": "Хапшења",
      "summary": "",
      "breaking": false,
      "alert": true,
      "priority": 100
    },
    {
      "id": "pom-zbog-ponizavanja-djordje-meloni-pljuste-reakcije-22zq20e",
      "title": "(FOTO,VIDEO) TRAMP SE POSVAĐAO SA ČITAVOM EVROPOM! Ponizio Đorđu Meloni, pa pokrenuo LAVINU: Dva lidera HITNO reagovala, a jednom od njih tek što je izašao iz zagrljaja",
      "url": "https://www.blic.rs/vesti/svet/tramp-u-svadji-sa-celom-evropom-zbog-ponizavanja-djordje-meloni-pljuste-reakcije/22zq20e",
      "date": "2026-06-19",
      "datetime": "2026-06-19T15:53:47+00:00",
      "time": "15:53",
      "source": "Blic",
      "category": "Људска права",
      "summary": "",
      "breaking": true,
      "alert": false,
      "priority": 100
    },
    {
      "id": "apsena-cetvorica-zbog-poreske-utaje-i-pranja-novca-u-ns-vest",
      "title": "Milionska prevara u Novom Sadu: Uhapšena četvorica zbog poreske utaje i pranja novca",
      "url": "https://www.euronews.rs/srbija/aktuelno/228768/uhapsena-cetvorica-zbog-poreske-utaje-i-pranja-novca-u-ns/vest",
      "date": "2026-06-18",
      "datetime": "2026-06-18T09:47:00+00:00",
      "time": "09:47",
      "source": "Euronews Serbia",
      "category": "Хапшења",
      "summary": "",
      "breaking": false,
      "alert": true,
      "priority": 100
    },
    {
      "id": "1tvo-zvu-c4-8dni-top-studenti-u-blokadi-srbija-33784467-html",
      "title": "Studenti u blokadi demantuju navode Tužilaštva o umešanosti u slučaj 'zvučnog topa'",
      "url": "https://www.slobodnaevropa.org/a/tu%c5%beila%c5%a1tvo-zvu%c4%8dni-top-studenti-u-blokadi-srbija/33784467.html",
      "date": "2026-06-19",
      "datetime": "2026-06-19T10:50:58+00:00",
      "time": "10:50",
      "source": "RSE Balkan",
      "category": "Криминал",
      "summary": "",
      "breaking": false,
      "alert": true,
      "priority": 94
    },
    {
      "id": "nika-hapsenje-u-beogradu-mahao-pistoljem-u-restoranu-vzrshhz",
      "title": "IZVADIO PIŠTOLJ U POZNATOM BEOGRADSKOM RESTORANU I UPERIO GA U MUŠKARCA? Filmska policijska potera: Napadač uhapšen na Gazeli",
      "url": "https://www.blic.rs/vesti/hronika/hapsenje-u-beogradu-mahao-pistoljem-u-restoranu/vzrshhz",
      "date": "2026-06-19",
      "datetime": "2026-06-19T21:27:53+00:00",
      "time": "21:27",
      "source": "Blic",
      "category": "Хапшења",
      "summary": "",
      "breaking": false,
      "alert": true,
      "priority": 92
    },
    {
      "id": "ladenovcu-bmw-om-udario-u-stajaliste-pa-pokosio-zenu-tv2bp8y",
      "title": "IZGUBIO KONTROLU NAD BMW-OM, UDARIO U STAJALIŠTE, PA POKOSIO ŽENU! Užas u Mladenovcu: Odmah je uhapšen",
      "url": "https://www.blic.rs/vesti/hronika/uzasna-nesreca-u-mladenovcu-bmw-om-udario-u-stajaliste-pa-pokosio-zenu/tv2bp8y",
      "date": "2026-06-19",
      "datetime": "2026-06-19T20:26:07+00:00",
      "time": "20:26",
      "source": "Blic",
      "category": "Хапшења",
      "summary": "",
      "breaking": false,
      "alert": true,
      "priority": 92
    },
    {
      "id": "od-mostarske-petlje-veliki-broj-policajaca-na-terenu-cpvj06f",
      "title": "HAPŠENJE KOD MOSTARSKE PETLJE! Veliki broj policajaca na terenu, pronađen i pištolj?",
      "url": "https://www.blic.rs/vesti/hronika/hapsenje-kod-mostarske-petlje-veliki-broj-policajaca-na-terenu/cpvj06f",
      "date": "2026-06-19",
      "datetime": "2026-06-19T20:07:12+00:00",
      "time": "20:07",
      "source": "Blic",
      "category": "Хапшења",
      "summary": "",
      "breaking": false,
      "alert": true,
      "priority": 92
    },
    {
      "id": "https-www-danas-rs-svet-u-jermeniji-uhapseni-opozicionari-",
      "title": "U Jermeniji uhapšeno više opozicionih političara, stranke traže ponavljanje glasanja na izborima",
      "url": "https://www.danas.rs/svet/u-jermeniji-uhapseni-opozicionari/",
      "date": "2026-06-19",
      "datetime": "2026-06-19T18:04:05+00:00",
      "time": "18:04",
      "source": "Danas",
      "category": "Хапшења",
      "summary": "",
      "breaking": false,
      "alert": true,
      "priority": 92
    },
    {
      "id": "h-politicara-stranke-traze-ponavljanje-glasanja-na-izborima-",
      "title": "U Jermeniji uhapšeno više opozicionih političara, stranke traže ponavljanje glasanja na izborima",
      "url": "https://n1info.rs/svet/u-jermeniji-uhapseno-vise-opozicionih-politicara-stranke-traze-ponavljanje-glasanja-na-izborima/",
      "date": "2026-06-19",
      "datetime": "2026-06-19T17:34:09+00:00",
      "time": "17:34",
      "source": "N1",
      "category": "Хапшења",
      "summary": "",
      "breaking": false,
      "alert": true,
      "priority": 92
    },
    {
      "id": "2-zaplenjeno-100-kg-droge-u-novom-sadu-uhapsena-dvojica-vest",
      "title": "Zaplenjeno 100 kilograma droge u Novom Sadu: Uhapšena dvojica osumnjičenih",
      "url": "https://www.euronews.rs/srbija/aktuelno/228772/zaplenjeno-100-kg-droge-u-novom-sadu-uhapsena-dvojica/vest",
      "date": "2026-06-18",
      "datetime": "2026-06-18T10:20:00+00:00",
      "time": "10:20",
      "source": "Euronews Serbia",
      "category": "Хапшења",
      "summary": "",
      "breaking": false,
      "alert": true,
      "priority": 92
    },
    {
      "id": "hapsena-dvojica-zbog-3-tone-neispravne-hrane-u-leskovcu-vest",
      "title": "Otkrivena hladnjača sa tri tone \"otrovne\" hrane u Leskovcu: Uhapšena dvojica osumnjičenih",
      "url": "https://www.euronews.rs/srbija/aktuelno/228771/uhapsena-dvojica-zbog-3-tone-neispravne-hrane-u-leskovcu/vest",
      "date": "2026-06-18",
      "datetime": "2026-06-18T09:31:00+00:00",
      "time": "09:31",
      "source": "Euronews Serbia",
      "category": "Хапшења",
      "summary": "",
      "breaking": false,
      "alert": true,
      "priority": 92
    },
    {
      "id": "opa-org-a-srbija-tuzioci-venecijanska-komisija-33783731-html",
      "title": "Smenjeni tužioci u Srbiji vraćeni na pozicije nakon preporuke Venecijanske komisije",
      "url": "https://www.slobodnaevropa.org/a/srbija-tuzioci-venecijanska-komisija/33783731.html",
      "date": "2026-06-18",
      "datetime": "2026-06-18T10:28:31+00:00",
      "time": "10:28",
      "source": "RSE Balkan",
      "category": "Криминал",
      "summary": "",
      "breaking": false,
      "alert": true,
      "priority": 90
    },
    {
      "id": "ako-zastititi-gradjane-od-zloupotreba-identiteta-i-korupcije",
      "title": "\"ORGANIZOVANI KRIMINAL NE POSTOJI BEZ KORUPCIJE!\" Stručnjaci upozoravaju posle afere sa lažnim identitetima: Ovo je najveća opasnost",
      "url": "https://www.kurir.rs/crna-hronika/10027015/kako-zastititi-gradjane-od-zloupotreba-identiteta-i-korupcije",
      "date": "2026-06-19",
      "datetime": "2026-06-19T18:33:30+00:00",
      "time": "18:33",
      "source": "Kurir",
      "category": "Криминал",
      "summary": "",
      "breaking": false,
      "alert": true,
      "priority": 84
    },
    {
      "id": "opa-org-a-srbija-kina-zidjing-prinudni-rad-sad-33784646-html",
      "title": "Srbija spasava kinesku kompaniju od američkih sankcija",
      "url": "https://www.slobodnaevropa.org/a/srbija-kina-zidjing-prinudni-rad-sad/33784646.html",
      "date": "2026-06-19",
      "datetime": "2026-06-19T15:29:55+00:00",
      "time": "15:29",
      "source": "RSE Balkan",
      "category": "Плате и зараде",
      "summary": "",
      "breaking": false,
      "alert": true,
      "priority": 74
    },
    {
      "id": "a-org-a-linglong-poginula-osoba-fabrika-srbija-33784363-html",
      "title": "Radnik Linglonga u Srbiji poginuo jer nije poštovao proces rada, saopštilo tužilaštvo",
      "url": "https://www.slobodnaevropa.org/a/linglong-poginula-osoba-fabrika-srbija/33784363.html",
      "date": "2026-06-19",
      "datetime": "2026-06-19T07:03:50+00:00",
      "time": "07:03",
      "source": "RSE Balkan",
      "category": "Тужилаштво",
      "summary": "",
      "breaking": false,
      "alert": true,
      "priority": 74
    },
    {
      "id": "a-hapsenja-u-novom-sadu-zbog-odavanja-mup-ovih-podataka-vest",
      "title": "Uhapšeno još osumnjičenih u slučaju bivšeg policajca koji je odavao podatke: Oglasilo se Više tužilaštvo u Novom Sadu",
      "url": "https://www.euronews.rs/srbija/aktuelno/228802/nova-hapsenja-u-novom-sadu-zbog-odavanja-mup-ovih-podataka/vest",
      "date": "2026-06-18",
      "datetime": "2026-06-18T12:44:00+00:00",
      "time": "12:44",
      "source": "Euronews Serbia",
      "category": "Тужилаштво",
      "summary": "",
      "breaking": false,
      "alert": true,
      "priority": 72
    },
    {
      "id": "s-2026-06-19-poginuo-radnik-u-fabrici-linglong-u-zrenjaninu-",
      "title": "Poginuo radnik u fabrici Linglong u Zrenjaninu",
      "url": "https://www.ktv.rs/2026/06/19/poginuo-radnik-u-fabrici-linglong-u-zrenjaninu/",
      "date": "2026-06-19",
      "datetime": "2026-06-19T11:37:55+00:00",
      "time": "11:37",
      "source": "KTV",
      "category": "Полиција",
      "summary": "",
      "breaking": false,
      "alert": true,
      "priority": 70
    },
    {
      "id": "-com-drustvo-poginuo-radnik-u-fabrici-linglong-u-zrenjaninu-",
      "title": "Poginuo radnik u fabrici Linglong u Zrenjaninu",
      "url": "https://vreme.com/drustvo/poginuo-radnik-u-fabrici-linglong-u-zrenjaninu/",
      "date": "2026-06-19",
      "datetime": "2026-06-19T07:11:07+00:00",
      "time": "07:11",
      "source": "Vreme",
      "category": "Полиција",
      "summary": "",
      "breaking": false,
      "alert": true,
      "priority": 70
    },
    {
      "id": "no-228826-u-automobilu-pronadene-bombe-i-raketni-bacaci-vest",
      "title": "Arsenal u gepeku: Uhapšen osumnjičeni za trgovinu oružjem u Nišu - zaplenjene bombe, automatske puške, raketni bacači",
      "url": "https://www.euronews.rs/srbija/aktuelno/228826/u-automobilu-pronadene-bombe-i-raketni-bacaci/vest",
      "date": "2026-06-18",
      "datetime": "2026-06-18T15:48:00+00:00",
      "time": "15:48",
      "source": "Euronews Serbia",
      "category": "Полиција",
      "summary": "",
      "breaking": false,
      "alert": true,
      "priority": 70
    },
    {
      "id": "naevropa-org-a-veran-matic-napadnut-u-beogradu-33783612-html",
      "title": "Napadnut novinar Veran Matić ispred Skupštine Srbije",
      "url": "https://www.slobodnaevropa.org/a/veran-matic-napadnut-u-beogradu/33783612.html",
      "date": "2026-06-18",
      "datetime": "2026-06-18T07:52:55+00:00",
      "time": "07:52",
      "source": "RSE Balkan",
      "category": "Полиција",
      "summary": "",
      "breaking": false,
      "alert": true,
      "priority": 70
    },
    {
      "id": "-pucao-u-svoj-narod-to-je-pokusaj-stvaranja-oruzanog-945fmx8",
      "title": "\"REKLI SU DA JE VUČIĆ PUCAO U SVOJ NAROD\" Advokat o aferi \"zvučni top\": \"To je direktan pokušaj stvaranja oružanog sukoba u Srbiji\"",
      "url": "https://www.blic.rs/vesti/politika/ljubicanovic-rekli-su-da-je-vucic-pucao-u-svoj-narod-to-je-pokusaj-stvaranja-oruzanog/945fmx8",
      "date": "2026-06-19",
      "datetime": "2026-06-19T20:03:57+00:00",
      "time": "20:03",
      "source": "Blic",
      "category": "Тужилаштво",
      "summary": "",
      "breaking": false,
      "alert": true,
      "priority": 66
    },
    {
      "id": "-pronaslo-dokaze-o-blokaderskom-planiranju-akcije-zvucni-top",
      "title": "Тужилаштво пронашло доказе о блокадерском планирању акције „звучни топ”",
      "url": "https://www.politika.rs/scc/clanak/764632/tuzilastvo-pronaslo-dokaze-o-blokaderskom-planiranju-akcije-zvucni-top",
      "date": "2026-06-19",
      "datetime": "2026-06-19T19:47:00+00:00",
      "time": "19:47",
      "source": "Politika",
      "category": "Тужилаштво",
      "summary": "",
      "breaking": false,
      "alert": true,
      "priority": 66
    },
    {
      "id": "rizma-skupi-podatke-procesuirace-se-cetiri-grupe-sa-plenuma-",
      "title": "Tužilac VJT: Nakon što Služba za borbu protiv terorizma skupi podatke, procesuiraće se četiri grupe sa plenuma",
      "url": "https://nova.rs/vesti/hronika/tuzilac-vjt-nakon-sto-sluzba-za-borbu-protiv-terorizma-skupi-podatke-procesuirace-se-cetiri-grupe-sa-plenuma/",
      "date": "2026-06-19",
      "datetime": "2026-06-19T19:34:23+00:00",
      "time": "19:34",
      "source": "Nova",
      "category": "Тужилаштво",
      "summary": "",
      "breaking": false,
      "alert": true,
      "priority": 66
    },
    {
      "id": "o-mladic-linglong-tuzilastvo-brzo-iznelo-detalje-firma-cuti-",
      "title": "Poginuo mladić u fabrici koja obećava \"bezbedno okruženje po meri\": Tužilaštvo okrivilo radnika, Linglong ćuti",
      "url": "https://n1info.rs/vesti/poginuo-mladic-linglong-tuzilastvo-brzo-iznelo-detalje-firma-cuti/",
      "date": "2026-06-19",
      "datetime": "2026-06-19T19:33:38+00:00",
      "time": "19:33",
      "source": "N1",
      "category": "Тужилаштво",
      "summary": "",
      "breaking": false,
      "alert": true,
      "priority": 66
    },
    {
      "id": "vjt-uskoro-procesuiranje-cetiri-grupe-sa-plenuma-zvucni-top-",
      "title": "Tužilac VJT: Nakon što Služba za borbu protiv terorizma skupi podatke, procesuiraće se četiri grupe lica",
      "url": "https://n1info.rs/vesti/tuzilac-vjt-uskoro-procesuiranje-cetiri-grupe-sa-plenuma-zvucni-top/",
      "date": "2026-06-19",
      "datetime": "2026-06-19T19:21:40+00:00",
      "time": "19:21",
      "source": "N1",
      "category": "Тужилаштво",
      "summary": "",
      "breaking": false,
      "alert": true,
      "priority": 66
    },
    {
      "id": "ikacija-cetiri-grupe-lica-u-vezi-sa-dogadjajima-od-15-marta-",
      "title": "Tužilac Miodrag Marković najavio identifikaciju i procesuiranje četiri grupe lica u vezi sa događajima od 15. marta",
      "url": "https://www.danas.rs/vesti/drustvo/tuzilac-miodrag-markovic-najavio-identifikacija-cetiri-grupe-lica-u-vezi-sa-dogadjajima-od-15-marta/",
      "date": "2026-06-19",
      "datetime": "2026-06-19T18:52:57+00:00",
      "time": "18:52",
      "source": "Danas",
      "category": "Тужилаштво",
      "summary": "",
      "breaking": false,
      "alert": true,
      "priority": 66
    },
    {
      "id": "vo-instruisano-ubedjivanje-javnosti-da-je-crno-zapravo-belo-",
      "title": "VJT istražuje navodnu „simulaciju zvučnog topa“: Instruisano ubeđivanje javnosti da je crno zapravo belo",
      "url": "https://www.danas.rs/vesti/drustvo/instruisano-ubedjivanje-javnosti-da-je-crno-zapravo-belo/",
      "date": "2026-06-19",
      "datetime": "2026-06-19T18:52:23+00:00",
      "time": "18:52",
      "source": "Danas",
      "category": "Тужилаштво",
      "summary": "",
      "breaking": false,
      "alert": true,
      "priority": 66
    },
    {
      "id": "se-studenti-optuzuju-za-pokusaj-izazivanja-gradjanskog-rata-",
      "title": "Novi spin o zvučnom topu pred novi protest: Tvrdnje idu toliko daleko da se studenti optužuju za pokušaj izazivanja građanskog rata",
      "url": "https://n1info.rs/vesti/novi-spin-o-zvucnom-topu-pred-novi-protest-tvrdnje-idu-toliko-daleko-da-se-studenti-optuzuju-za-pokusaj-izazivanja-gradjanskog-rata/",
      "date": "2026-06-19",
      "datetime": "2026-06-19T18:08:25+00:00",
      "time": "18:08",
      "source": "N1",
      "category": "Тужилаштво",
      "summary": "",
      "breaking": false,
      "alert": true,
      "priority": 66
    },
    {
      "id": "s-rs-vesti-hronika-5977183-zvucni-top-vjt-dokumentacija-html",
      "title": "Барац: Документација указује на припремане сценарије; Бјеговић: МУП нема звучни топ, пуна истина ће бити обелодањена",
      "url": "https://www.rts.rs/vesti/hronika/5977183/zvucni-top-vjt-dokumentacija.html",
      "date": "2026-06-19",
      "datetime": "2026-06-19T17:50:03+00:00",
      "time": "17:50",
      "source": "RTS",
      "category": "Тужилаштво",
      "summary": "",
      "breaking": false,
      "alert": true,
      "priority": 66
    },
    {
      "id": "erznim-saopstenjem-pokrenulo-kampanju-targetiranja-novinara-",
      "title": "Koalicija za slobodu medija: VJT kontroverznim saopštenjem pokrenulo kampanju targetiranja novinara",
      "url": "https://www.danas.rs/vesti/drustvo/koalicija-za-slobodu-medija-vjt-kontroverznim-saopstenjem-pokrenulo-kampanju-targetiranja-novinara/",
      "date": "2026-06-19",
      "datetime": "2026-06-19T15:55:09+00:00",
      "time": "15:55",
      "source": "Danas",
      "category": "Тужилаштво",
      "summary": "",
      "breaking": false,
      "alert": true,
      "priority": 66
    },
    {
      "id": "-tekst-objavljen-na-portalu-novars-o-istrazi-o-zvucnom-topu-",
      "title": "VJT reagovalo na tekst objavljen na portalu Nova.rs o istrazi o “zvučnom topu”",
      "url": "https://nova.rs/vesti/hronika/vjt-reagovao-na-tekst-objavljen-na-portalu-novars-o-istrazi-o-zvucnom-topu/",
      "date": "2026-06-19",
      "datetime": "2026-06-19T15:32:30+00:00",
      "time": "15:32",
      "source": "Nova",
      "category": "Тужилаштво",
      "summary": "",
      "breaking": false,
      "alert": true,
      "priority": 66
    },
    {
      "id": "strazuje-da-li-su-za-slucaj-zvucnog-topa-odgovorni-studenti-",
      "title": "Tužilaštvo u Beogradu istražuje da li su za slučaj ‘zvučnog topa’ odgovorni studenti",
      "url": "https://www.ktv.rs/2026/06/19/tuzilastvo-u-beogradu-istrazuje-da-li-su-za-slucaj-zvucnog-topa-odgovorni-studenti/",
      "date": "2026-06-19",
      "datetime": "2026-06-19T13:05:39+00:00",
      "time": "13:05",
      "source": "KTV",
      "category": "Тужилаштво",
      "summary": "",
      "breaking": false,
      "alert": true,
      "priority": 66
    },
    {
      "id": "-ustavnog-poretka-studenti-zvucni-top-vise-javno-tuzilastvo-",
      "title": "Da li VJT priprema nove tužbe protiv studenata zbog navodnog pokušaja nasilnog rušenja ustavnog poretka?",
      "url": "https://vreme.com/vesti/rusenje-ustavnog-poretka-studenti-zvucni-top-vise-javno-tuzilastvo/",
      "date": "2026-06-19",
      "datetime": "2026-06-19T12:58:02+00:00",
      "time": "12:58",
      "source": "Vreme",
      "category": "Тужилаштво",
      "summary": "",
      "breaking": false,
      "alert": true,
      "priority": 66
    },
    {
      "id": "lobodnaevropa-org-a-ribnikar-presuda-roditelji-33783689-html",
      "title": "Presuda za masakr u školi 'Ribnikar': Ocu 14 i po godina zatvora, majci dve godine i 11 meseci",
      "url": "https://www.slobodnaevropa.org/a/ribnikar-presuda-roditelji/33783689.html",
      "date": "2026-06-18",
      "datetime": "2026-06-18T09:13:34+00:00",
      "time": "09:13",
      "source": "RSE Balkan",
      "category": "Тужилаштво",
      "summary": "",
      "breaking": false,
      "alert": true,
      "priority": 66
    },
    {
      "id": "https-www-krik-rs-veselin-milic-ostaje-u-pritvoru-",
      "title": "Veselin Milić ostaje u pritvoru",
      "url": "https://www.krik.rs/veselin-milic-ostaje-u-pritvoru/",
      "date": "2026-06-12",
      "datetime": "2026-06-12T14:33:17+00:00",
      "time": "14:33",
      "source": "KRIK",
      "category": "Тужилаштво",
      "summary": "",
      "breaking": false,
      "alert": true,
      "priority": 66
    },
    {
      "id": "ti-ponovo-pokusavali-da-ospore-dokaze-na-sudjenju-jovanjica-",
      "title": "Advokati ponovo pokušavali da ospore dokaze na suđenju „Jovanjica“",
      "url": "https://www.krik.rs/advokati-ponovo-pokusavali-da-ospore-dokaze-na-sudjenju-jovanjica/",
      "date": "2026-06-11",
      "datetime": "2026-06-11T17:08:22+00:00",
      "time": "17:08",
      "source": "KRIK",
      "category": "Тужилаштво",
      "summary": "",
      "breaking": false,
      "alert": true,
      "priority": 66
    },
    {
      "id": "ilic-nije-bio-u-restoranu-na-senjaku-kada-je-ubijen-nesovic-",
      "title": "Tužilaštvo: Milić nije bio u restoranu na Senjaku kada je ubijen Nešović",
      "url": "https://www.krik.rs/tuzilastvo-milic-nije-bio-u-restoranu-na-senjaku-kada-je-ubijen-nesovic/",
      "date": "2026-06-10",
      "datetime": "2026-06-10T08:38:27+00:00",
      "time": "08:38",
      "source": "KRIK",
      "category": "Тужилаштво",
      "summary": "",
      "breaking": false,
      "alert": true,
      "priority": 66
    },
    {
      "id": "-danas-rs-vesti-drustvo-birodi-rem-rts-zvucni-top-pravilnik-",
      "title": "BIRODI: RTS emitovanjem emisije o zvučnom topu prekršio odredbe Pravilnika o zaštiti ljudskih prava u oblasti pružanja medijskih usluga",
      "url": "https://www.danas.rs/vesti/drustvo/birodi-rem-rts-zvucni-top-pravilnik/",
      "date": "2026-06-19",
      "datetime": "2026-06-19T21:21:08+00:00",
      "time": "21:21",
      "source": "Danas",
      "category": "Људска права",
      "summary": "",
      "breaking": false,
      "alert": true,
      "priority": 60
    },
    {
      "id": "vo-je-dokument-u-kom-se-prvi-put-spominje-zvucni-top-vcw9mnt",
      "title": "(FOTO) OVO JE DOKUMENT U KOM SE PRVI PUT SPOMINJE \"ZVUČNI TOP\" Zapisnik sa sastanka Studenata u blokadi i rekonstrukcija događaja sa protesta 15. marta objavljeni na RTS",
      "url": "https://www.blic.rs/vesti/politika/foto-ovo-je-dokument-u-kom-se-prvi-put-spominje-zvucni-top/vcw9mnt",
      "date": "2026-06-19",
      "datetime": "2026-06-19T18:45:05+00:00",
      "time": "18:45",
      "source": "Blic",
      "category": "Људска права",
      "summary": "",
      "breaking": false,
      "alert": true,
      "priority": 60
    },
    {
      "id": "ala-preporuke-o-sprecavanju-korucpije-u-vrhu-izvrsne-vlasti-",
      "title": "GREKO izveštaj: Srbija nije do kraja ispoštovala preporuke o sprečavanju korucpije u vrhu izvršne vlasti",
      "url": "https://nova.rs/vesti/politika/greko-izvestaj-srbija-nije-do-kraja-ispostovala-preporuke-o-sprecavanju-korucpije-u-vrhu-izvrsne-vlasti/",
      "date": "2026-06-19",
      "datetime": "2026-06-19T15:42:03+00:00",
      "time": "15:42",
      "source": "Nova",
      "category": "Корупција",
      "summary": "",
      "breaking": false,
      "alert": false,
      "priority": 30
    },
    {
      "id": "cije-pokrenula-vanrednu-proveru-imovine-djedovic-handanovic-",
      "title": "Agencija za sprečavanje korupcije pokrenula vanrednu proveru imovine Đedović Handanović",
      "url": "https://www.ktv.rs/2026/06/19/agencija-za-sprecavanje-korupcije-pokrenula-vanrednu-proveru-imovine-djedovic-handanovic/",
      "date": "2026-06-19",
      "datetime": "2026-06-19T14:07:37+00:00",
      "time": "14:07",
      "source": "KTV",
      "category": "Корупција",
      "summary": "",
      "breaking": false,
      "alert": false,
      "priority": 30
    },
    {
      "id": "36-parandiloviceva-kartica-predmet-provere-u-parlamentu-vest",
      "title": "Brnabić: Ispitati navode o Parandilovićevoj zloupotrebi službene kartice u Skupštini",
      "url": "https://www.euronews.rs/srbija/politika/228836/parandiloviceva-kartica-predmet-provere-u-parlamentu/vest",
      "date": "2026-06-18",
      "datetime": "2026-06-18T16:58:00+00:00",
      "time": "16:58",
      "source": "Euronews Serbia",
      "category": "Злоупотребе",
      "summary": "",
      "breaking": false,
      "alert": false,
      "priority": 28
    },
    {
      "id": "ps-radar-nova-rs-drustvo-novi-radar-najavni-tekst-mup-krimi-",
      "title": "Novi Radar: Kako policija obezbeđuje kriminalce",
      "url": "https://radar.nova.rs/drustvo/novi-radar-najavni-tekst-mup-krimi/",
      "date": "2026-06-17",
      "datetime": "2026-06-17T17:00:00+00:00",
      "time": "17:00",
      "source": "Radar",
      "category": "Криминал",
      "summary": "",
      "breaking": false,
      "alert": false,
      "priority": 28
    },
    {
      "id": "lucaju-generalstab-selakovic-targetiran-casno-obavlja-posao-",
      "title": "Sekretarka Ministarstva kulture iznela odbranu u slučaju „Generalštab“: Selaković targetiran, časno obavlja posao",
      "url": "https://www.krik.rs/sekretarka-ministarstva-kulture-iznela-odbranu-u-slucaju-generalstab-selakovic-targetiran-casno-obavlja-posao/",
      "date": "2026-06-10",
      "datetime": "2026-06-10T12:58:38+00:00",
      "time": "12:58",
      "source": "KRIK",
      "category": "Злоупотребе",
      "summary": "",
      "breaking": false,
      "alert": false,
      "priority": 28
    },
    {
      "id": "-suspendovan-disciplinski-postupak-medjunarodni-krivicni-sud",
      "title": "BRITANCI SUSPENDOVALI TUŽIOCA KOJI JE IZDAO NALOGE ZA HAPŠENJE PUTINA I NETANJAHUA: Kan čeka odluku o smeni zbog optužbi za neprikladne odnose sa saradnicom",
      "url": "https://www.kurir.rs/planeta/10027782/karim-kan-suspendovan-disciplinski-postupak-medjunarodni-krivicni-sud",
      "date": "2026-06-19",
      "datetime": "2026-06-19T19:56:37+00:00",
      "time": "19:56",
      "source": "Kurir",
      "category": "Хапшења",
      "summary": "",
      "breaking": false,
      "alert": false,
      "priority": 26
    },
    {
      "id": "ika-10027602-ovo-je-ubijeni-srbin-u-barseloni-kristijan-kiki",
      "title": "KO JE UBIJENI SRBIN U BARSELONI: Kiki dobro poznat policiji, hapšen zbog kokaina još 2017, pa dogurao do balkanskog kartela!",
      "url": "https://www.kurir.rs/crna-hronika/10027602/ovo-je-ubijeni-srbin-u-barseloni-kristijan-kiki",
      "date": "2026-06-19",
      "datetime": "2026-06-19T16:50:57+00:00",
      "time": "16:50",
      "source": "Kurir",
      "category": "Хапшења",
      "summary": "",
      "breaking": false,
      "alert": false,
      "priority": 26
    }
  ],
  "all_sources": [
    "AP News",
    "Al Jazeera Balkans",
    "Amnesty",
    "B92",
    "BBC Serbian",
    "BIRN",
    "Beta",
    "Blic",
    "CINS",
    "CRTA",
    "Council of Europe",
    "DW Balkan",
    "Danas",
    "EU Commission",
    "EU Serbia",
    "Euronews Serbia",
    "FoNet",
    "France24",
    "Građanske inicijative",
    "Human Rights Watch",
    "Informer",
    "Insajder",
    "KRIK",
    "KTV",
    "Kurir",
    "N1",
    "NIN",
    "Nova",
    "Novosti",
    "OHCHR",
    "OSCE Serbia",
    "Pink",
    "Politika",
    "RSE Balkan",
    "RTS",
    "RTV",
    "Radar",
    "Reuters",
    "Tanjug",
    "The Guardian World",
    "Transparency Serbia",
    "UN Serbia",
    "VOA Balkan",
    "Vreme",
    "YUCOM"
  ]
}