[
  {
    "winner": null,
    "accepted": 2346900.0,
    "lowest": 6202.0,
    "difference": 2340698.0,
    "status": "SUMNJIVO",
    "suspicious": true,
    "rejection_reasons": [],
    "id": 100664803,
    "file": "documents/100664803_Odluka o dodeli ugovora.docx"
  },
  {
    "winner": null,
    "accepted": 400000000.0,
    "lowest": 1296.0,
    "difference": 399998704.0,
    "status": "SUMNJIVO",
    "suspicious": true,
    "rejection_reasons": [],
    "id": 100454087,
    "file": "documents/100454087_Odluka o dodeli Astra Kikinda.pdf"
  },
  {
    "winner": null,
    "accepted": 5000000.0,
    "lowest": 6202.0,
    "difference": 4993798.0,
    "status": "SUMNJIVO",
    "suspicious": true,
    "rejection_reasons": [],
    "id": 101637029,
    "file": "documents/101637029_Odluka o dodeli ugovora - 0001-2026-2  P2.docx"
  },
  {
    "winner": null,
    "accepted": 28000.0,
    "lowest": 1202.0,
    "difference": 26798.0,
    "status": "SUMNJIVO",
    "suspicious": true,
    "rejection_reasons": [],
    "id": 100038783,
    "file": "documents/100038783_ODLUKA 051-26-D.pdf"
  },
  {
    "winner": null,
    "accepted": 6202.0,
    "lowest": 5202.0,
    "difference": 1000.0,
    "status": "SUMNJIVO",
    "suspicious": true,
    "rejection_reasons": [],
    "id": 102156404,
    "file": "documents/102156404_Odluka o dodeli.docx"
  },
  {
    "winner": null,
    "accepted": 6202.0,
    "lowest": 5202.0,
    "difference": 1000.0,
    "status": "SUMNJIVO",
    "suspicious": true,
    "rejection_reasons": [],
    "id": 101534073,
    "file": "documents/101534073_Odluka o dodeli.docx"
  },
  {
    "winner": null,
    "accepted": 6202.0,
    "lowest": 5202.0,
    "difference": 1000.0,
    "status": "SUMNJIVO",
    "suspicious": true,
    "rejection_reasons": [],
    "id": 112295021,
    "file": "documents/112295021_Odluka o dodeli.docx"
  },
  {
    "winner": null,
    "accepted": 6202.0,
    "lowest": 5202.0,
    "difference": 1000.0,
    "status": "SUMNJIVO",
    "suspicious": true,
    "rejection_reasons": [],
    "id": 100345259,
    "file": "documents/100345259_Odluka o dodeli.docx"
  },
  {
    "winner": null,
    "accepted": 6202.0,
    "lowest": 5202.0,
    "difference": 1000.0,
    "status": "SUMNJIVO",
    "suspicious": true,
    "rejection_reasons": [],
    "id": 101822498,
    "file": "documents/101822498_Odluka o dodeli.docx"
  }
]